smartapi/__init__.py
smartapi/base.py
smartapi/decorators.py
smartapi/errors.py
smartapi/logs.py
smartapi/model_fields.py
smartapi/utils.py
smartapi/custom_fields/__init__.py
smartapi/custom_fields/mixins.py
smartapi/custom_fields/model.py
smartapi/custom_fields/query.py
smartapi/custom_fields/schema.py
smartapi/custom_fields/data/__init__.py
smartapi/custom_fields/data/row/__init__.py
smartapi/custom_fields/data/row/model.py
smartapi/custom_fields/data/row/query.py
smartapi/custom_fields/data/value/__init__.py
smartapi/custom_fields/data/value/model.py
smartapi/custom_fields/data/value/query.py
smartapi/custom_fields/set/__init__.py
smartapi/custom_fields/set/model.py
smartapi/custom_fields/set/query.py
smartapi/custom_fields/type/__init__.py
smartapi/custom_fields/type/model.py
smartbox_smartapi-0.0.10.dist-info/LICENSE
smartbox_smartapi-0.0.10.dist-info/METADATA
smartbox_smartapi-0.0.10.dist-info/WHEEL
smartbox_smartapi-0.0.10.dist-info/top_level.txt
smartbox_smartapi-0.0.10.dist-info/RECORD
